nstools/Fs/BaseFs.py
nstools/Fs/Bktr.py
nstools/Fs/Cnmt.py
nstools/Fs/File.py
nstools/Fs/Hfs0.py
nstools/Fs/Ivfc.py
nstools/Fs/Nacp.py
nstools/Fs/Nca.py
nstools/Fs/Nsp.py
nstools/Fs/Pfs0.py
nstools/Fs/Rom.py
nstools/Fs/Ticket.py
nstools/Fs/Type.py
nstools/Fs/Xci.py
nstools/Fs/__init__.py
nstools/lib/BlockDecompressorReader.py
nstools/lib/FsCert.py
nstools/lib/FsNcaMod.py
nstools/lib/FsTools.py
nstools/lib/Header.py
nstools/lib/NcaKeys.py
nstools/lib/PathTools.py
nstools/lib/Verify.py
nstools/lib/VerifyTools.py
nstools/nut/Hex.py
nstools/nut/Keys.py
nstools/nut/Print.py
nstools/nut/Titles.py
nstools/nut/aes128.py
nstools-1.2.3.data/scripts/ns-verify-folder
nstools-1.2.3.data/scripts/ns-verify-folder-log
nstools-1.2.3.data/scripts/ns-verify-folder-log.bat
nstools-1.2.3.data/scripts/ns-verify-folder.bat
nstools-1.2.3.data/scripts/ns_verify_folder.py
nstools-1.2.3.dist-info/licenses/LICENSE.md
nstools-1.2.3.dist-info/METADATA
nstools-1.2.3.dist-info/WHEEL
nstools-1.2.3.dist-info/top_level.txt
nstools-1.2.3.dist-info/zip-safe
nstools-1.2.3.dist-info/RECORD
