Metadata-Version: 2.4
Name: nstools
Version: 1.2.3
Home-page: https://github.com/seiya-dev/NSTools
License: MIT
Requires-Python: >=3.10
License-File: LICENSE.md
Requires-Dist: zstandard
Requires-Dist: enlighten
Requires-Dist: requests
Requires-Dist: pycryptodome
Dynamic: description
Dynamic: description-content-type
Dynamic: home-page
Dynamic: license
Dynamic: license-file
Dynamic: requires-dist
Dynamic: requires-python
